{
  "name": "top-landing-pages-30-days",
  "query": {
    "dimensions": [
      {
        "name": "hostName"
      },
      {
        "name": "landingPagePlusQueryString"
      }
    ],
    "metrics": [
      {
        "name": "screenPageViews"
      },
      {
        "name": "sessions"
      },
      {
        "name": "activeUsers"
      },
      {
        "name": "screenPageViewsPerSession"
      },
      {
        "name": "averageSessionDuration"
      },
      {
        "name": "bounceRate"
      }
    ],
    "orderBys": [
      {
        "metric": {
          "metricName": "screenPageViews"
        },
        "desc": true
      }
    ],
    "dateRanges": [
      {
        "startDate": "30daysAgo",
        "endDate": "yesterday"
      }
    ],
    "limit": "20",
    "samplingLevel": "HIGHER_PRECISION",
    "property": "properties/395458906"
  },
  "meta": {
    "name": "Top Landing Pages (30 Days)",
    "description": "Last 30 days' Landing Pages, measured by visits, for all sites."
  },
  "data": [
    {
      "domain": "(other)",
      "landing_page": "(other)",
      "pageviews": "3702951",
      "visits": "5593747",
      "active_visitors": "3991165",
      "pageviews_per_session": "0.66198042206771235",
      "avg_session_duration": "81.23982051521601",
      "bounce_rate": "0.40817362672998975"
    },
    {
      "domain": "www.ecfr.gov",
      "landing_page": "/",
      "pageviews": "637144",
      "visits": "128537",
      "active_visitors": "84099",
      "pageviews_per_session": "4.9568917899126319",
      "avg_session_duration": "365.38538214654153",
      "bounce_rate": "0.20198853248480983"
    },
    {
      "domain": "www.archives.gov",
      "landing_page": "/",
      "pageviews": "410090",
      "visits": "169526",
      "active_visitors": "134589",
      "pageviews_per_session": "2.4190389674740156",
      "avg_session_duration": "165.44758042687846",
      "bounce_rate": "0.36417422696223589"
    },
    {
      "domain": "www.federalregister.gov",
      "landing_page": "/",
      "pageviews": "367888",
      "visits": "103589",
      "active_visitors": "61892",
      "pageviews_per_session": "3.5514195522690635",
      "avg_session_duration": "273.72730630210737",
      "bounce_rate": "0.26722914595179026"
    },
    {
      "domain": "vetrecs.archives.gov",
      "landing_page": "/veterans/military-service-records",
      "pageviews": "288652",
      "visits": "43691",
      "active_visitors": "38772",
      "pageviews_per_session": "6.60666956581447",
      "avg_session_duration": "458.970535514202",
      "bounce_rate": "0.0075072669428486415"
    },
    {
      "domain": "vetrecs.archives.gov",
      "landing_page": "/VeteranRequest/pg/LANDING_1.htm",
      "pageviews": "279580",
      "visits": "89943",
      "active_visitors": "50201",
      "pageviews_per_session": "3.1084131060782942",
      "avg_session_duration": "220.44950635370179",
      "bounce_rate": "0.28234548547413363"
    },
    {
      "domain": "www.archives.gov",
      "landing_page": "/founding-docs/declaration-transcript",
      "pageviews": "168794",
      "visits": "151648",
      "active_visitors": "122777",
      "pageviews_per_session": "1.1130644650770205",
      "avg_session_duration": "177.38591597484304",
      "bounce_rate": "0.5124828550327073"
    },
    {
      "domain": "www.federalregister.gov",
      "landing_page": "/documents/search",
      "pageviews": "167605",
      "visits": "57610",
      "active_visitors": "43623",
      "pageviews_per_session": "2.9093039402881442",
      "avg_session_duration": "225.72750421142163",
      "bounce_rate": "0.533674709251866"
    },
    {
      "domain": "www.ecfr.gov",
      "landing_page": "/current/title-38/chapter-I/part-4",
      "pageviews": "154849",
      "visits": "108493",
      "active_visitors": "35422",
      "pageviews_per_session": "1.4272718055542755",
      "avg_session_duration": "245.19384218863888",
      "bounce_rate": "0.50513858036924042"
    },
    {
      "domain": "www.archives.gov",
      "landing_page": "/veterans/military-service-records",
      "pageviews": "154588",
      "visits": "82629",
      "active_visitors": "70435",
      "pageviews_per_session": "1.870868581248714",
      "avg_session_duration": "146.60141473776761",
      "bounce_rate": "0.24875043870795968"
    },
    {
      "domain": "www.archives.gov",
      "landing_page": "/founding-docs/constitution-transcript",
      "pageviews": "151254",
      "visits": "113476",
      "active_visitors": "91402",
      "pageviews_per_session": "1.3329162113574677",
      "avg_session_duration": "231.5931394926416",
      "bounce_rate": "0.421842504141845"
    },
    {
      "domain": "vetrecs.archives.gov",
      "landing_page": "/",
      "pageviews": "116395",
      "visits": "18179",
      "active_visitors": "14705",
      "pageviews_per_session": "6.4027174212002862",
      "avg_session_duration": "464.59345247670387",
      "bounce_rate": "0.0021453325265416139"
    },
    {
      "domain": "www.ecfr.gov",
      "landing_page": "/current/title-14",
      "pageviews": "112028",
      "visits": "21319",
      "active_visitors": "14663",
      "pageviews_per_session": "5.2548430977062717",
      "avg_session_duration": "422.970184642291",
      "bounce_rate": "0.13302687743327549"
    },
    {
      "domain": "www.archives.gov",
      "landing_page": "/research/military",
      "pageviews": "101326",
      "visits": "21926",
      "active_visitors": "20530",
      "pageviews_per_session": "4.6212715497582781",
      "avg_session_duration": "207.84201676881329",
      "bounce_rate": "0.062026817476967984"
    },
    {
      "domain": "www.archives.gov",
      "landing_page": "/founding-docs/bill-of-rights/what-does-it-say",
      "pageviews": "98590",
      "visits": "89472",
      "active_visitors": "72358",
      "pageviews_per_session": "1.1019089771101573",
      "avg_session_duration": "192.6570784651735",
      "bounce_rate": "0.49011981402002863"
    },
    {
      "domain": "www.ecfr.gov",
      "landing_page": "/search",
      "pageviews": "96104",
      "visits": "22476",
      "active_visitors": "13675",
      "pageviews_per_session": "4.2758497953372485",
      "avg_session_duration": "428.55508695230463",
      "bounce_rate": "0.26009966186154121"
    },
    {
      "domain": "www.archives.gov",
      "landing_page": "/electoral-college/allocation",
      "pageviews": "89809",
      "visits": "92041",
      "active_visitors": "81811",
      "pageviews_per_session": "0.97574993752784089",
      "avg_session_duration": "113.17990721220978",
      "bounce_rate": "0.50995751893178043"
    },
    {
      "domain": "www.archives.gov",
      "landing_page": "/publications/prologue/2005/winter/von-trapps-html",
      "pageviews": "85152",
      "visits": "86844",
      "active_visitors": "75243",
      "pageviews_per_session": "0.98051678872460968",
      "avg_session_duration": "264.001661632905",
      "bounce_rate": "0.52677214315324028"
    },
    {
      "domain": "georgewbush-whitehouse.archives.gov",
      "landing_page": "/history/presidents/chronological.html",
      "pageviews": "85090",
      "visits": "66766",
      "active_visitors": "62369",
      "pageviews_per_session": "1.2744510679088159",
      "avg_session_duration": "115.71111533810623",
      "bounce_rate": "0.45241590030854029"
    },
    {
      "domain": "aad.archives.gov",
      "landing_page": "/research/military/ww2",
      "pageviews": "84114",
      "visits": "4484",
      "active_visitors": "4357",
      "pageviews_per_session": "18.758697591436217",
      "avg_session_duration": "412.65324224531668",
      "bounce_rate": "0.0022301516503122213"
    }
  ],
  "totals": {
    "visits": 7066396
  },
  "taken_at": "2024-01-05T15:48:58.930Z",
  "agency": "national-archives-records-administration"
}